qt_life_cli/__init__.py
qt_life_cli/main.py
qt_life_cli-0.0.11.dist-info/METADATA
qt_life_cli-0.0.11.dist-info/WHEEL
qt_life_cli-0.0.11.dist-info/entry_points.txt
qt_life_cli-0.0.11.dist-info/top_level.txt
qt_life_cli-0.0.11.dist-info/RECORD
