Metadata-Version: 2.1
Name: qt-life-cli
Version: 0.0.11
Author: Anonymous
Author-email: anonymous@qtlife.com
Classifier: Programming Language :: Python :: 3
Classifier: License :: OSI Approved :: MIT License
Classifier: Operating System :: OS Independent
Requires-Python: >=3.7
Requires-Dist: Click ==8.1.3
Requires-Dist: prompt-toolkit ==3.0.38
Requires-Dist: colorama ==0.4.6
